goodbudget_cli/__init__.py
goodbudget_cli/config.json
goodbudget_cli/run_goodbudget.py
goodbudget_cli/utils/__init__.py
goodbudget_cli/utils/driver.py
goodbudget_cli/utils/util.py
goodbudget_cli-0.2.1.dist-info/LICENSE
goodbudget_cli-0.2.1.dist-info/METADATA
goodbudget_cli-0.2.1.dist-info/WHEEL
goodbudget_cli-0.2.1.dist-info/entry_points.txt
goodbudget_cli-0.2.1.dist-info/top_level.txt
goodbudget_cli-0.2.1.dist-info/RECORD
