Metadata-Version: 2.1
Name: goodbudget-cli
Version: 0.2.1
Summary: A command line tool for interacting with Goodbudget
Home-page: https://github.com/yphillip/goodbudget_cli
Author: Phillip Yen
Author-email: yphillip@gmail.com
Requires-Python: >=3.7
License-File: LICENSE
Requires-Dist: selenium (>=4.7.2)
Provides-Extra: test
Requires-Dist: pytest ; extra == 'test'
